qree.py
qree-0.0.4.dist-info/LICENSE.txt
qree-0.0.4.dist-info/WHEEL
qree-0.0.4.dist-info/METADATA
qree-0.0.4.dist-info/RECORD
