Metadata-Version: 2.1
Name: qree
Version: 0.0.4
Summary: Qree: Tiny but mighty Python templating.
Home-page: https://github.com/polydojo/qree
License: UNKNOWN
Author: Polydojo, Inc.
Author-email: 8079593+sumukhbarve@users.noreply.github.com
Classifier: License :: OSI Approved :: MIT License
